hilary/__init__.py
hilary/__main__.py
hilary/apriori.py
hilary/cdfs_326651.csv
hilary/cdfs_326713.csv
hilary/cdfs_paired.csv
hilary/cdfs_paired_post_50K.csv
hilary/expectmax.py
hilary/inference.py
hilary/utils.py
hilary/__pycache__/__init__.cpython-310.pyc
hilary/__pycache__/__init__.cpython-311.pyc
hilary/__pycache__/__main__.cpython-310.pyc
hilary/__pycache__/apriori.cpython-310.pyc
hilary/__pycache__/apriori_full.cpython-310.pyc
hilary/__pycache__/binomiale_expect_max.cpython-310.pyc
hilary/__pycache__/cdr3_clustering.cpython-310.pyc
hilary/__pycache__/distance_matrix.compute_distance_matrix_fast-44.py310.1.nbc
hilary/__pycache__/distance_matrix.compute_distance_matrix_fast-44.py310.nbi
hilary/__pycache__/distance_matrix.compute_distance_matrix_fast-66.py310.1.nbc
hilary/__pycache__/distance_matrix.compute_distance_matrix_fast-66.py310.nbi
hilary/__pycache__/distance_matrix.compute_distance_matrix_fast-71.py310.1.nbc
hilary/__pycache__/distance_matrix.compute_distance_matrix_fast-71.py310.nbi
hilary/__pycache__/distance_matrix.compute_metric_fast-15.py310.1.nbc
hilary/__pycache__/distance_matrix.compute_metric_fast-15.py310.nbi
hilary/__pycache__/distance_matrix.compute_metric_fast-37.py310.1.nbc
hilary/__pycache__/distance_matrix.compute_metric_fast-37.py310.nbi
hilary/__pycache__/distance_matrix.compute_metric_fast-41.py310.1.nbc
hilary/__pycache__/distance_matrix.compute_metric_fast-41.py310.nbi
hilary/__pycache__/distance_matrix.cpython-310.pyc
hilary/__pycache__/distance_matrix.hamming_bytes_fast-10.py310.1.nbc
hilary/__pycache__/distance_matrix.hamming_bytes_fast-10.py310.nbi
hilary/__pycache__/distance_matrix.hamming_bytes_fast-32.py310.1.nbc
hilary/__pycache__/distance_matrix.hamming_bytes_fast-32.py310.nbi
hilary/__pycache__/distance_matrix.hamming_bytes_fast-35.py310.1.nbc
hilary/__pycache__/distance_matrix.hamming_bytes_fast-35.py310.nbi
hilary/__pycache__/expectmax.cpython-310.pyc
hilary/__pycache__/inference.cpython-310.pyc
hilary-1.2.4.dist-info/licenses/LICENSE
hilary-1.2.4.dist-info/METADATA
hilary-1.2.4.dist-info/WHEEL
hilary-1.2.4.dist-info/entry_points.txt
hilary-1.2.4.dist-info/top_level.txt
hilary-1.2.4.dist-info/RECORD
