Metadata-Version: 2.4
Name: hilary
Version: 1.2.4
Home-page: https://github.com/statbiophys/HILARy/
Author: Gabriel Athènes,Natanael Spisak
Author-email: gabriel.athenes@polytechnique.edu,natanael.spisak@gmail.com
Classifier: Intended Audience :: Developers
Classifier: Programming Language :: Python
Classifier: Programming Language :: Python :: 3
Classifier: Programming Language :: Python :: 3.10
License-File: LICENSE
Requires-Dist: setuptools>=56
Requires-Dist: numpy<3,>=1.20.0
Requires-Dist: openpyxl<4,>=3.1
Requires-Dist: pandas<3,>=2.2
Requires-Dist: scipy<2,>=1.6
Requires-Dist: structlog<23,>=22.3.0
Requires-Dist: textdistance<5,>=4.6
Requires-Dist: tqdm<5,>=4.66
Requires-Dist: typer<1,>=0.9
Requires-Dist: atriegc<1.0.0,>=0.0.3
Requires-Dist: scipy<2,>1.11
Dynamic: author
Dynamic: author-email
Dynamic: classifier
Dynamic: home-page
Dynamic: license-file
Dynamic: requires-dist
